ultrasphere_harmonics/__init__.py
ultrasphere_harmonics/__main__.py
ultrasphere_harmonics/_cut.py
ultrasphere_harmonics/_expansion.py
ultrasphere_harmonics/_helmholtz.py
ultrasphere_harmonics/_ndim.py
ultrasphere_harmonics/_translation.py
ultrasphere_harmonics/cli.py
ultrasphere_harmonics/py.typed
ultrasphere_harmonics/_core/__init__.py
ultrasphere_harmonics/_core/_assume.py
ultrasphere_harmonics/_core/_concat.py
ultrasphere_harmonics/_core/_eigenfunction.py
ultrasphere_harmonics/_core/_expand_dim.py
ultrasphere_harmonics/_core/_flatten.py
ultrasphere_harmonics/_core/_harmonics.py
ultrasphere_harmonics-1.2.0.dist-info/licenses/LICENSE
ultrasphere_harmonics-1.2.0.dist-info/METADATA
ultrasphere_harmonics-1.2.0.dist-info/WHEEL
ultrasphere_harmonics-1.2.0.dist-info/entry_points.txt
ultrasphere_harmonics-1.2.0.dist-info/top_level.txt
ultrasphere_harmonics-1.2.0.dist-info/RECORD
