Metadata-Version: 2.4
Name: ultrasphere-harmonics
Version: 1.2.0
Summary: Hyperspherical harmonics in NumPy / PyTorch / JAX
Author-email: 34j <34j.95a2p@simplelogin.com>
License: MIT
Project-URL: Bug Tracker, https://github.com/ultrasphere-dev/ultrasphere-harmonics/issues
Project-URL: Changelog, https://github.com/ultrasphere-dev/ultrasphere-harmonics/blob/main/CHANGELOG.md
Project-URL: documentation, https://ultrasphere-harmonics.readthedocs.io
Project-URL: repository, https://github.com/ultrasphere-dev/ultrasphere-harmonics
Classifier: Development Status :: 2 - Pre-Alpha
Classifier: Intended Audience :: Developers
Classifier: Natural Language :: English
Classifier: Operating System :: OS Independent
Classifier: Programming Language :: Python :: 3.12
Classifier: Programming Language :: Python :: 3.13
Classifier: Topic :: Software Development :: Libraries
Requires-Python: >=3.12
License-File: LICENSE
Requires-Dist: array-api-negative-index>=1.0.0
Requires-Dist: gumerov-expansion-coefficients>=1.2.0
Requires-Dist: jacobi-poly>=1.0.4
Requires-Dist: shift-nth-row-n-steps>=1.0.0
Requires-Dist: ultrasphere>=2.0.0
Provides-Extra: cli
Requires-Dist: aquarel>=0.0.7; extra == "cli"
Requires-Dist: cyclopts>=3.24.0; extra == "cli"
Requires-Dist: open3d-cpu>=0.19.0; extra == "cli"
Requires-Dist: rich>=10; extra == "cli"
Requires-Dist: typer<1,>=0.15; extra == "cli"
Dynamic: license-file
